{
  "cards" : [
  {
    "cardName":"Eye Patch",
    "cardText": "Hotdog",
    "cardCost":"3",
    "image":"1"
  },
  {
    "cardName":"Some Words",
    "cardText": "Hoasdtdog",
    "cardCost":"3asd",
    "image":"2"
  },
  {
    "cardName":"Donkey",
    "cardText": "Hoasdtdog",
    "cardCost":"3asd",
    "image":"1"
  },
  {
    "cardName":"Stop Watch",
    "cardText": "Hoasdtdog",
    "cardCost":"3asd",
    "image":"1"
  },
  {
    "cardName":"MTG",
    "cardText": "Hoasdtdog",
    "cardCost":"3asd",
    "image":"3"
  },
  {
    "cardName":"Weeb",
    "cardText": "Hoasdtdog",
    "cardCost":"3asd",
    "image":"4"
  },
  {
    "cardName":"Nack",
    "cardText": "Hoasdtdog",
    "cardCost":"3asd",
    "image":"5"
  },
  {
    "cardName":"Jutin",
    "cardText": "Hoasdtdog",
    "cardCost":"3asd",
    "image":"2"
  },
  {
    "cardName":"Nack 2",
    "cardText": "Hotdog",
    "cardCost":"3",
    "image":"1"
  }
]
}
